{
	"metadata": {
		"version": 5,
		"type": "Object",
		"generator": "Object3D.toJSON"
	},
	"geometries": [
		{
			"uuid": "72503450-9431-4270-991D-26CD12B6A4B4",
			"type": "BoxGeometry",
			"width": 10,
			"height": 2,
			"depth": 10,
			"widthSegments": 1,
			"heightSegments": 1,
			"depthSegments": 1
		},
		{
			"uuid": "50E4ABE4-0C88-4396-AB52-9A2744682793",
			"type": "BoxGeometry",
			"width": 10,
			"height": 5,
			"depth": 2,
			"widthSegments": 1,
			"heightSegments": 1,
			"depthSegments": 1
		},
		{
			"uuid": "B4176CD5-321B-4723-92C0-68BFDFF71973",
			"type": "BoxGeometry",
			"width": 10,
			"height": 8,
			"depth": 2,
			"widthSegments": 1,
			"heightSegments": 1,
			"depthSegments": 1
		},
		{
			"uuid": "A9AEB414-6794-4031-A2DF-52F4568B416E",
			"type": "BoxGeometry",
			"width": 2,
			"height": 8,
			"depth": 10,
			"widthSegments": 1,
			"heightSegments": 1,
			"depthSegments": 1
		},
		{
			"uuid": "579DB1D9-430D-48E9-A8A4-5844ADB31C7A",
			"type": "BoxGeometry",
			"width": 2,
			"height": 8,
			"depth": 10,
			"widthSegments": 1,
			"heightSegments": 1,
			"depthSegments": 1
		},
		{
			"uuid": "74B9BF35-9397-4291-BE1F-E91B09ED790E",
			"type": "BoxGeometry",
			"width": 10,
			"height": 2,
			"depth": 12,
			"widthSegments": 1,
			"heightSegments": 1,
			"depthSegments": 1
		},
		{
			"uuid": "37DE508D-8F0E-4218-B3F7-9A6CC33B6395",
			"type": "BoxGeometry",
			"width": 5,
			"height": 8,
			"depth": 2,
			"widthSegments": 1,
			"heightSegments": 1,
			"depthSegments": 1
		},
		{
			"uuid": "EE076D3F-0656-4A13-AEFE-303BAB66C67D",
			"type": "BoxGeometry",
			"width": 5,
			"height": 8,
			"depth": 2,
			"widthSegments": 1,
			"heightSegments": 1,
			"depthSegments": 1
		},
		{
			"uuid": "16F26A45-6C9D-4B40-9CC0-E30BE3A37CB9",
			"type": "BoxGeometry",
			"width": 2,
			"height": 8,
			"depth": 7,
			"widthSegments": 1,
			"heightSegments": 1,
			"depthSegments": 1
		},
		{
			"uuid": "9010FF0F-252F-4E12-8EBE-133AC5FCC84B",
			"type": "BoxGeometry",
			"width": 2,
			"height": 8,
			"depth": 7,
			"widthSegments": 1,
			"heightSegments": 1,
			"depthSegments": 1
		},
		{
			"uuid": "02456791-C372-45FD-94DC-10469602B8F0",
			"type": "BoxGeometry",
			"width": 20,
			"height": 2,
			"depth": 2,
			"widthSegments": 1,
			"heightSegments": 1,
			"depthSegments": 1
		},
		{
			"uuid": "842BA6AC-B470-4B78-8B27-05119E74CC26",
			"type": "BoxGeometry",
			"width": 20,
			"height": 4,
			"depth": 2,
			"widthSegments": 1,
			"heightSegments": 1,
			"depthSegments": 1
		},
		{
			"uuid": "7AF8F0D7-7191-4DA2-93C8-073C33E2F487",
			"type": "BoxGeometry",
			"width": 20,
			"height": 2,
			"depth": 8,
			"widthSegments": 1,
			"heightSegments": 1,
			"depthSegments": 1
		},
		{
			"uuid": "2863B4BE-B740-4FCC-9720-315EBA4BEE4F",
			"type": "BoxGeometry",
			"width": 8,
			"height": 2,
			"depth": 2,
			"widthSegments": 1,
			"heightSegments": 1,
			"depthSegments": 1
		},
		{
			"uuid": "7DDC34DC-C138-4ECE-98A9-AAFE90E13CF8",
			"type": "BoxGeometry",
			"width": 20,
			"height": 2,
			"depth": 10,
			"widthSegments": 1,
			"heightSegments": 1,
			"depthSegments": 1
		}],
	"materials": [
		{
			"uuid": "22651893-A1B5-4BBB-8A3E-986DE5318A24",
			"type": "MeshStandardMaterial",
			"color": 16777215,
			"roughness": 1,
			"metalness": 0,
			"emissive": 0,
			"envMapIntensity": 1,
			"refractionRatio": 1,
			"depthFunc": 3,
			"depthTest": true,
			"depthWrite": true,
			"colorWrite": true,
			"stencilWrite": false,
			"stencilWriteMask": 255,
			"stencilFunc": 519,
			"stencilRef": 0,
			"stencilFuncMask": 255,
			"stencilFail": 7680,
			"stencilZFail": 7680,
			"stencilZPass": 7680
		},
		{
			"uuid": "8B050A90-E2AA-4C3F-BDF7-5C11248758BC",
			"type": "MeshStandardMaterial",
			"color": 16777215,
			"roughness": 1,
			"metalness": 0,
			"emissive": 0,
			"envMapIntensity": 1,
			"refractionRatio": 1,
			"depthFunc": 3,
			"depthTest": true,
			"depthWrite": true,
			"colorWrite": true,
			"stencilWrite": false,
			"stencilWriteMask": 255,
			"stencilFunc": 519,
			"stencilRef": 0,
			"stencilFuncMask": 255,
			"stencilFail": 7680,
			"stencilZFail": 7680,
			"stencilZPass": 7680
		},
		{
			"uuid": "A83009EB-8625-42D5-86DD-419D953F9282",
			"type": "MeshStandardMaterial",
			"color": 16777215,
			"roughness": 1,
			"metalness": 0,
			"emissive": 0,
			"envMapIntensity": 1,
			"refractionRatio": 1,
			"depthFunc": 3,
			"depthTest": true,
			"depthWrite": true,
			"colorWrite": true,
			"stencilWrite": false,
			"stencilWriteMask": 255,
			"stencilFunc": 519,
			"stencilRef": 0,
			"stencilFuncMask": 255,
			"stencilFail": 7680,
			"stencilZFail": 7680,
			"stencilZPass": 7680
		},
		{
			"uuid": "6FDD6F7A-1F19-4370-95C9-E4C14F907599",
			"type": "MeshStandardMaterial",
			"color": 16777215,
			"roughness": 1,
			"metalness": 0,
			"emissive": 0,
			"envMapIntensity": 1,
			"refractionRatio": 1,
			"depthFunc": 3,
			"depthTest": true,
			"depthWrite": true,
			"colorWrite": true,
			"stencilWrite": false,
			"stencilWriteMask": 255,
			"stencilFunc": 519,
			"stencilRef": 0,
			"stencilFuncMask": 255,
			"stencilFail": 7680,
			"stencilZFail": 7680,
			"stencilZPass": 7680
		},
		{
			"uuid": "2E94B205-B23C-4359-AB05-A18A8398BE91",
			"type": "MeshStandardMaterial",
			"color": 16777215,
			"roughness": 1,
			"metalness": 0,
			"emissive": 0,
			"envMapIntensity": 1,
			"refractionRatio": 1,
			"depthFunc": 3,
			"depthTest": true,
			"depthWrite": true,
			"colorWrite": true,
			"stencilWrite": false,
			"stencilWriteMask": 255,
			"stencilFunc": 519,
			"stencilRef": 0,
			"stencilFuncMask": 255,
			"stencilFail": 7680,
			"stencilZFail": 7680,
			"stencilZPass": 7680
		},
		{
			"uuid": "0BD3F4A4-4217-438E-A06E-2C5AEBB847A2",
			"type": "MeshStandardMaterial",
			"color": 16777215,
			"roughness": 1,
			"metalness": 0,
			"emissive": 0,
			"envMapIntensity": 1,
			"refractionRatio": 1,
			"depthFunc": 3,
			"depthTest": true,
			"depthWrite": true,
			"colorWrite": true,
			"stencilWrite": false,
			"stencilWriteMask": 255,
			"stencilFunc": 519,
			"stencilRef": 0,
			"stencilFuncMask": 255,
			"stencilFail": 7680,
			"stencilZFail": 7680,
			"stencilZPass": 7680
		},
		{
			"uuid": "4CD89473-9F81-4C74-83BF-DEE5F5FB076B",
			"type": "MeshStandardMaterial",
			"color": 16777215,
			"roughness": 1,
			"metalness": 0,
			"emissive": 0,
			"envMapIntensity": 1,
			"refractionRatio": 1,
			"depthFunc": 3,
			"depthTest": true,
			"depthWrite": true,
			"colorWrite": true,
			"stencilWrite": false,
			"stencilWriteMask": 255,
			"stencilFunc": 519,
			"stencilRef": 0,
			"stencilFuncMask": 255,
			"stencilFail": 7680,
			"stencilZFail": 7680,
			"stencilZPass": 7680
		},
		{
			"uuid": "8517DB87-7DCD-4DAE-B514-B05383F73C3F",
			"type": "MeshStandardMaterial",
			"color": 16777215,
			"roughness": 1,
			"metalness": 0,
			"emissive": 0,
			"envMapIntensity": 1,
			"refractionRatio": 1,
			"depthFunc": 3,
			"depthTest": true,
			"depthWrite": true,
			"colorWrite": true,
			"stencilWrite": false,
			"stencilWriteMask": 255,
			"stencilFunc": 519,
			"stencilRef": 0,
			"stencilFuncMask": 255,
			"stencilFail": 7680,
			"stencilZFail": 7680,
			"stencilZPass": 7680
		},
		{
			"uuid": "A632BCCD-9D7E-40FA-8A05-52D28D25C5EF",
			"type": "MeshStandardMaterial",
			"color": 16777215,
			"roughness": 1,
			"metalness": 0,
			"emissive": 0,
			"envMapIntensity": 1,
			"refractionRatio": 1,
			"depthFunc": 3,
			"depthTest": true,
			"depthWrite": true,
			"colorWrite": true,
			"stencilWrite": false,
			"stencilWriteMask": 255,
			"stencilFunc": 519,
			"stencilRef": 0,
			"stencilFuncMask": 255,
			"stencilFail": 7680,
			"stencilZFail": 7680,
			"stencilZPass": 7680
		},
		{
			"uuid": "21AC9738-1244-4816-ABB8-5518115FB887",
			"type": "MeshStandardMaterial",
			"color": 16777215,
			"roughness": 1,
			"metalness": 0,
			"emissive": 0,
			"envMapIntensity": 1,
			"refractionRatio": 1,
			"depthFunc": 3,
			"depthTest": true,
			"depthWrite": true,
			"colorWrite": true,
			"stencilWrite": false,
			"stencilWriteMask": 255,
			"stencilFunc": 519,
			"stencilRef": 0,
			"stencilFuncMask": 255,
			"stencilFail": 7680,
			"stencilZFail": 7680,
			"stencilZPass": 7680
		}],
	"object": {
		"uuid": "36492C3F-620C-4082-9283-A154FFEB34D6",
		"type": "Scene",
		"name": "Scene",
		"layers": 1,
		"matrix": [1,0,0,0,0,1,0,0,0,0,1,0,0,0,0,1],
		"children": [
			{
				"uuid": "A4BD479B-C9C3-435A-BF4C-D7E128357D2F",
				"type": "Mesh",
				"name": "Box",
				"layers": 1,
				"matrix": [1,0,0,0,0,1,0,0,0,0,1,0,0,-1,0,1],
				"geometry": "72503450-9431-4270-991D-26CD12B6A4B4",
				"material": "22651893-A1B5-4BBB-8A3E-986DE5318A24"
			},
			{
				"uuid": "70096515-2A2A-4DBC-86B7-416AF41EC8AC",
				"type": "Mesh",
				"name": "unplaceable_0",
				"layers": 1,
				"matrix": [1,0,0,0,0,1,0,0,0,0,1,0,0,3,6,1],
				"geometry": "50E4ABE4-0C88-4396-AB52-9A2744682793",
				"material": "8B050A90-E2AA-4C3F-BDF7-5C11248758BC"
			},
			{
				"uuid": "7B180322-1C69-472E-98FC-D72016A73E85",
				"type": "Mesh",
				"name": "Box",
				"layers": 1,
				"matrix": [1,0,0,0,0,1,0,0,0,0,1,0,0,4,-6,1],
				"geometry": "B4176CD5-321B-4723-92C0-68BFDFF71973",
				"material": "A83009EB-8625-42D5-86DD-419D953F9282"
			},
			{
				"uuid": "3FFDAFF8-3002-4079-B48E-30FB0A82B087",
				"type": "Mesh",
				"name": "Box",
				"layers": 1,
				"matrix": [1,0,0,0,0,1,0,0,0,0,1,0,6,4,0,1],
				"geometry": "A9AEB414-6794-4031-A2DF-52F4568B416E",
				"material": "6FDD6F7A-1F19-4370-95C9-E4C14F907599"
			},
			{
				"uuid": "6BA8832E-72F4-4986-A1C2-899928E5688B",
				"type": "Mesh",
				"name": "Box",
				"layers": 1,
				"matrix": [1,0,0,0,0,1,0,0,0,0,1,0,-6,4,0,1],
				"geometry": "579DB1D9-430D-48E9-A8A4-5844ADB31C7A",
				"material": "2E94B205-B23C-4359-AB05-A18A8398BE91"
			},
			{
				"uuid": "BB0D9025-8896-46C3-B0A1-B95E61A618AD",
				"type": "Mesh",
				"name": "Box",
				"layers": 1,
				"matrix": [1,0,0,0,0,1,0,0,0,0,1,0,0,9,1,1],
				"geometry": "74B9BF35-9397-4291-BE1F-E91B09ED790E",
				"material": "0BD3F4A4-4217-438E-A06E-2C5AEBB847A2"
			},
			{
				"uuid": "59852322-436C-4B68-8D46-030CB52C7C3E",
				"type": "Mesh",
				"name": "unplaceable_2",
				"layers": 1,
				"matrix": [1,0,0,0,0,1,0,0,0,0,1,0,-8,4,6,1],
				"geometry": "37DE508D-8F0E-4218-B3F7-9A6CC33B6395",
				"material": "4CD89473-9F81-4C74-83BF-DEE5F5FB076B"
			},
			{
				"uuid": "D80F3480-2DD2-47A8-9729-EBE30EB754CC",
				"type": "Mesh",
				"name": "unplaceable_1",
				"layers": 1,
				"matrix": [1,0,0,0,0,1,0,0,0,0,1,0,8,4,6,1],
				"geometry": "EE076D3F-0656-4A13-AEFE-303BAB66C67D",
				"material": "8517DB87-7DCD-4DAE-B514-B05383F73C3F"
			},
			{
				"uuid": "F5AF83C6-6B4A-4D1C-A301-0C684ABB36D1",
				"type": "Mesh",
				"name": "Box",
				"layers": 1,
				"matrix": [1,0,0,0,0,1,0,0,0,0,1,0,-9,4,10,1],
				"geometry": "16F26A45-6C9D-4B40-9CC0-E30BE3A37CB9",
				"material": "A632BCCD-9D7E-40FA-8A05-52D28D25C5EF"
			},
			{
				"uuid": "436A0CBE-24EB-42AB-8E64-4C124910919D",
				"type": "Mesh",
				"name": "Box",
				"layers": 1,
				"matrix": [1,0,0,0,0,1,0,0,0,0,1,0,9,4,10,1],
				"geometry": "9010FF0F-252F-4E12-8EBE-133AC5FCC84B",
				"material": "21AC9738-1244-4816-ABB8-5518115FB887"
			},
			{
				"uuid": "5445DCF5-35FF-4BFB-AA8D-73FB37CAAD1B",
				"type": "Mesh",
				"name": "unplaceable_3",
				"layers": 1,
				"matrix": [1,0,0,0,0,1,0,0,0,0,1,0,0,1,14,1],
				"geometry": "02456791-C372-45FD-94DC-10469602B8F0",
				"material": "8B050A90-E2AA-4C3F-BDF7-5C11248758BC"
			},
			{
				"uuid": "A7076D19-D067-48B5-AC32-44DAACCEAA39",
				"type": "Mesh",
				"name": "unplaceable_4",
				"layers": 1,
				"matrix": [1,0,0,0,0,1,0,0,0,0,1,0,0,6,14,1],
				"geometry": "842BA6AC-B470-4B78-8B27-05119E74CC26",
				"material": "8B050A90-E2AA-4C3F-BDF7-5C11248758BC"
			},
			{
				"uuid": "22F79132-4283-4E9F-838B-BD6F9511283A",
				"type": "Mesh",
				"name": "Box",
				"layers": 1,
				"matrix": [1,0,0,0,0,1,0,0,0,0,1,0,0,9,11,1],
				"geometry": "7AF8F0D7-7191-4DA2-93C8-073C33E2F487",
				"material": "0BD3F4A4-4217-438E-A06E-2C5AEBB847A2"
			},
			{
				"uuid": "89B747D0-CDAC-44B8-9824-4F0424F9232E",
				"type": "Mesh",
				"name": "unplaceable_5",
				"layers": 1,
				"matrix": [1,0,0,0,0,1,0,0,0,0,1,0,-6,3,14,1],
				"geometry": "2863B4BE-B740-4FCC-9720-315EBA4BEE4F",
				"material": "8B050A90-E2AA-4C3F-BDF7-5C11248758BC"
			},
			{
				"uuid": "BA698DE0-8DB4-4EBE-B1D1-E986D80798D4",
				"type": "Mesh",
				"name": "unplaceable_6",
				"layers": 1,
				"matrix": [1,0,0,0,0,1,0,0,0,0,1,0,6,3,14,1],
				"geometry": "2863B4BE-B740-4FCC-9720-315EBA4BEE4F",
				"material": "8B050A90-E2AA-4C3F-BDF7-5C11248758BC"
			},
			{
				"uuid": "6B5A1EE0-0DB0-4519-88B7-6F5D0493E8C6",
				"type": "Mesh",
				"name": "Box",
				"layers": 1,
				"matrix": [1,0,0,0,0,1,0,0,0,0,1,0,0,-1,10,1],
				"geometry": "7DDC34DC-C138-4ECE-98A9-AAFE90E13CF8",
				"material": "22651893-A1B5-4BBB-8A3E-986DE5318A24"
			}],
		"environment": {
			"metadata": {
				"version": 5,
				"type": "Texture",
				"generator": "Texture.toJSON"
			},
			"uuid": "2C0F91EE-ABCF-43B2-8F88-7C3BD6D36A62",
			"name": "PMREM.cubeUv",
			"mapping": 306,
			"repeat": [1,1],
			"offset": [0,0],
			"center": [0,0],
			"rotation": 0,
			"wrap": [1001,1001],
			"format": 1023,
			"type": 1009,
			"encoding": 3002,
			"minFilter": 1003,
			"magFilter": 1003,
			"anisotropy": 1,
			"flipY": true,
			"premultiplyAlpha": false,
			"unpackAlignment": 4,
			"image": "68F31F75-15CC-4CC1-99F2-19D925AA990A"
		}
	}
}